[
  {
    "intensity": -3,
    "r": 0,
    "g": 0,
    "b": 205
  },
  {
    "intensity": -2.9,
    "r": 0,
    "g": 7,
    "b": 209
  },
  {
    "intensity": -2.8,
    "r": 0,
    "g": 14,
    "b": 214
  },
  {
    "intensity": -2.7,
    "r": 0,
    "g": 21,
    "b": 218
  },
  {
    "intensity": -2.6,
    "r": 0,
    "g": 28,
    "b": 223
  },
  {
    "intensity": -2.5,
    "r": 0,
    "g": 36,
    "b": 227
  },
  {
    "intensity": -2.4,
    "r": 0,
    "g": 43,
    "b": 231
  },
  {
    "intensity": -2.3,
    "r": 0,
    "g": 50,
    "b": 236
  },
  {
    "intensity": -2.2,
    "r": 0,
    "g": 57,
    "b": 240
  },
  {
    "intensity": -2.1,
    "r": 0,
    "g": 64,
    "b": 245
  },
  {
    "intensity": -2,
    "r": 0,
    "g": 72,
    "b": 250
  },
  {
    "intensity": -1.9,
    "r": 0,
    "g": 85,
    "b": 238
  },
  {
    "intensity": -1.8,
    "r": 0,
    "g": 99,
    "b": 227
  },
  {
    "intensity": -1.7,
    "r": 0,
    "g": 112,
    "b": 216
  },
  {
    "intensity": -1.6,
    "r": 0,
    "g": 126,
    "b": 205
  },
  {
    "intensity": -1.5,
    "r": 0,
    "g": 140,
    "b": 194
  },
  {
    "intensity": -1.4,
    "r": 0,
    "g": 153,
    "b": 183
  },
  {
    "intensity": -1.3,
    "r": 0,
    "g": 167,
    "b": 172
  },
  {
    "intensity": -1.2,
    "r": 0,
    "g": 180,
    "b": 161
  },
  {
    "intensity": -1.1,
    "r": 0,
    "g": 194,
    "b": 150
  },
  {
    "intensity": -1,
    "r": 0,
    "g": 208,
    "b": 139
  },
  {
    "intensity": -0.9,
    "r": 6,
    "g": 212,
    "b": 130
  },
  {
    "intensity": -0.8,
    "r": 12,
    "g": 216,
    "b": 121
  },
  {
    "intensity": -0.7,
    "r": 18,
    "g": 220,
    "b": 113
  },
  {
    "intensity": -0.6,
    "r": 25,
    "g": 224,
    "b": 104
  },
  {
    "intensity": -0.5,
    "r": 31,
    "g": 228,
    "b": 96
  },
  {
    "intensity": -0.4,
    "r": 37,
    "g": 233,
    "b": 88
  },
  {
    "intensity": -0.3,
    "r": 44,
    "g": 237,
    "b": 79
  },
  {
    "intensity": -0.2,
    "r": 50,
    "g": 241,
    "b": 71
  },
  {
    "intensity": -0.1,
    "r": 56,
    "g": 245,
    "b": 62
  },
  {
    "intensity": 0,
    "r": 63,
    "g": 250,
    "b": 54
  },
  {
    "intensity": 0.1,
    "r": 75,
    "g": 250,
    "b": 49
  },
  {
    "intensity": 0.2,
    "r": 88,
    "g": 250,
    "b": 45
  },
  {
    "intensity": 0.3,
    "r": 100,
    "g": 251,
    "b": 41
  },
  {
    "intensity": 0.4,
    "r": 113,
    "g": 251,
    "b": 37
  },
  {
    "intensity": 0.5,
    "r": 125,
    "g": 252,
    "b": 33
  },
  {
    "intensity": 0.6,
    "r": 138,
    "g": 252,
    "b": 28
  },
  {
    "intensity": 0.7,
    "r": 151,
    "g": 253,
    "b": 24
  },
  {
    "intensity": 0.8,
    "r": 163,
    "g": 253,
    "b": 20
  },
  {
    "intensity": 0.9,
    "r": 176,
    "g": 254,
    "b": 16
  },
  {
    "intensity": 1,
    "r": 189,
    "g": 255,
    "b": 12
  },
  {
    "intensity": 1.1,
    "r": 195,
    "g": 254,
    "b": 10
  },
  {
    "intensity": 1.2,
    "r": 202,
    "g": 254,
    "b": 9
  },
  {
    "intensity": 1.3,
    "r": 208,
    "g": 254,
    "b": 8
  },
  {
    "intensity": 1.4,
    "r": 215,
    "g": 254,
    "b": 7
  },
  {
    "intensity": 1.5,
    "r": 222,
    "g": 255,
    "b": 5
  },
  {
    "intensity": 1.6,
    "r": 228,
    "g": 254,
    "b": 4
  },
  {
    "intensity": 1.7,
    "r": 235,
    "g": 255,
    "b": 3
  },
  {
    "intensity": 1.8,
    "r": 241,
    "g": 254,
    "b": 2
  },
  {
    "intensity": 1.9,
    "r": 248,
    "g": 255,
    "b": 1
  },
  {
    "intensity": 2,
    "r": 255,
    "g": 255,
    "b": 0
  },
  {
    "intensity": 2.1,
    "r": 254,
    "g": 251,
    "b": 0
  },
  {
    "intensity": 2.2,
    "r": 254,
    "g": 248,
    "b": 0
  },
  {
    "intensity": 2.3,
    "r": 254,
    "g": 244,
    "b": 0
  },
  {
    "intensity": 2.4,
    "r": 254,
    "g": 241,
    "b": 0
  },
  {
    "intensity": 2.5,
    "r": 255,
    "g": 238,
    "b": 0
  },
  {
    "intensity": 2.6,
    "r": 254,
    "g": 234,
    "b": 0
  },
  {
    "intensity": 2.7,
    "r": 255,
    "g": 231,
    "b": 0
  },
  {
    "intensity": 2.8,
    "r": 254,
    "g": 227,
    "b": 0
  },
  {
    "intensity": 2.9,
    "r": 255,
    "g": 224,
    "b": 0
  },
  {
    "intensity": 3,
    "r": 255,
    "g": 221,
    "b": 0
  },
  {
    "intensity": 3.1,
    "r": 254,
    "g": 213,
    "b": 0
  },
  {
    "intensity": 3.2,
    "r": 254,
    "g": 205,
    "b": 0
  },
  {
    "intensity": 3.3,
    "r": 254,
    "g": 197,
    "b": 0
  },
  {
    "intensity": 3.4,
    "r": 254,
    "g": 190,
    "b": 0
  },
  {
    "intensity": 3.5,
    "r": 255,
    "g": 182,
    "b": 0
  },
  {
    "intensity": 3.6,
    "r": 254,
    "g": 174,
    "b": 0
  },
  {
    "intensity": 3.7,
    "r": 255,
    "g": 167,
    "b": 0
  },
  {
    "intensity": 3.8,
    "r": 254,
    "g": 159,
    "b": 0
  },
  {
    "intensity": 3.9,
    "r": 255,
    "g": 151,
    "b": 0
  },
  {
    "intensity": 4,
    "r": 255,
    "g": 144,
    "b": 0
  },
  {
    "intensity": 4.1,
    "r": 254,
    "g": 136,
    "b": 0
  },
  {
    "intensity": 4.2,
    "r": 254,
    "g": 128,
    "b": 0
  },
  {
    "intensity": 4.3,
    "r": 254,
    "g": 121,
    "b": 0
  },
  {
    "intensity": 4.4,
    "r": 254,
    "g": 113,
    "b": 0
  },
  {
    "intensity": 4.5,
    "r": 255,
    "g": 106,
    "b": 0
  },
  {
    "intensity": 4.6,
    "r": 254,
    "g": 98,
    "b": 0
  },
  {
    "intensity": 4.7,
    "r": 255,
    "g": 90,
    "b": 0
  },
  {
    "intensity": 4.8,
    "r": 254,
    "g": 83,
    "b": 0
  },
  {
    "intensity": 4.9,
    "r": 255,
    "g": 75,
    "b": 0
  },
  {
    "intensity": 5,
    "r": 255,
    "g": 68,
    "b": 0
  },
  {
    "intensity": 5.1,
    "r": 254,
    "g": 61,
    "b": 0
  },
  {
    "intensity": 5.2,
    "r": 253,
    "g": 54,
    "b": 0
  },
  {
    "intensity": 5.3,
    "r": 252,
    "g": 47,
    "b": 0
  },
  {
    "intensity": 5.4,
    "r": 251,
    "g": 40,
    "b": 0
  },
  {
    "intensity": 5.5,
    "r": 250,
    "g": 33,
    "b": 0
  },
  {
    "intensity": 5.6,
    "r": 249,
    "g": 27,
    "b": 0
  },
  {
    "intensity": 5.7,
    "r": 248,
    "g": 20,
    "b": 0
  },
  {
    "intensity": 5.8,
    "r": 247,
    "g": 13,
    "b": 0
  },
  {
    "intensity": 5.9,
    "r": 246,
    "g": 6,
    "b": 0
  },
  {
    "intensity": 6,
    "r": 245,
    "g": 0,
    "b": 0
  },
  {
    "intensity": 6.1,
    "r": 238,
    "g": 0,
    "b": 0
  },
  {
    "intensity": 6.2,
    "r": 230,
    "g": 0,
    "b": 0
  },
  {
    "intensity": 6.3,
    "r": 223,
    "g": 0,
    "b": 0
  },
  {
    "intensity": 6.4,
    "r": 215,
    "g": 0,
    "b": 0
  },
  {
    "intensity": 6.5,
    "r": 208,
    "g": 0,
    "b": 0
  },
  {
    "intensity": 6.6,
    "r": 200,
    "g": 0,
    "b": 0
  },
  {
    "intensity": 6.7,
    "r": 192,
    "g": 0,
    "b": 0
  },
  {
    "intensity": 6.8,
    "r": 185,
    "g": 0,
    "b": 0
  },
  {
    "intensity": 6.9,
    "r": 177,
    "g": 0,
    "b": 0
  },
  {
    "intensity": 7,
    "r": 170,
    "g": 0,
    "b": 0
  }
]
